<?xml version="1.0" encoding="utf-8"?>
<Catalog>


    <CSound id="acObj_ShakurasAlly_1222" parent="ACVO_Priority" Portrait="RohanaEx2Portrait" Subtitle="acObj" Speaker="ShakurasAlly" Actor="RohanaEx2Portrait" Line="01222"><Flags index="NeedsUpdate" value="1"/><Flags index="NeedsTTS" value="1"/></CSound>
    <CSound id="acObj_ShakurasAlly_1223" parent="ACVO_Priority" Portrait="RohanaEx2Portrait" Subtitle="acObj" Speaker="ShakurasAlly" Actor="RohanaEx2Portrait" Line="01223"><Flags index="NeedsUpdate" value="1"/><Flags index="NeedsTTS" value="1"/></CSound>
    <CSound id="acObj_ShakurasAlly_1224" parent="ACVO_Priority" Portrait="RohanaEx2Portrait" Subtitle="acObj" Speaker="ShakurasAlly" Actor="RohanaEx2Portrait" Line="01224"><Flags index="NeedsUpdate" value="1"/><Flags index="NeedsTTS" value="1"/></CSound>
    <CSound id="acObj_ShakurasAlly_1096" parent="ACVO_Priority" Portrait="RohanaEx2Portrait" Subtitle="acObj" Speaker="ShakurasAlly" Actor="RohanaEx2Portrait" Line="01096"><Flags index="NeedsUpdate" value="1"/><Flags index="NeedsTTS" value="1"/></CSound>
    <CSound id="acObj_ShakurasAlly_1098" parent="ACVO_Priority" Portrait="RohanaEx2Portrait" Subtitle="acObj" Speaker="ShakurasAlly" Actor="RohanaEx2Portrait" Line="01098"><Flags index="NeedsUpdate" value="1"/><Flags index="NeedsTTS" value="1"/></CSound>
    <CSound id="acObj_ShakurasAlly_1100" parent="ACVO_Priority" Portrait="RohanaEx2Portrait" Subtitle="acObj" Speaker="ShakurasAlly" Actor="RohanaEx2Portrait" Line="01100"><Flags index="NeedsUpdate" value="1"/><Flags index="NeedsTTS" value="1"/></CSound>
    <CSound id="acObj_ShakurasAlly_1102" parent="ACVO_Priority" Portrait="RohanaEx2Portrait" Subtitle="acObj" Speaker="ShakurasAlly" Actor="RohanaEx2Portrait" Line="01102"><Flags index="NeedsUpdate" value="1"/><Flags index="NeedsTTS" value="1"/></CSound>
    <CSound id="acObj_ShakurasAlly_1105" parent="ACVO_Priority" Portrait="RohanaEx2Portrait" Subtitle="acObj" Speaker="ShakurasAlly" Actor="RohanaEx2Portrait" Line="01105"><Flags index="NeedsUpdate" value="1"/><Flags index="NeedsTTS" value="1"/></CSound>
    <CSound id="acObj_ShakurasAlly_1108" parent="ACVO_Priority" Portrait="RohanaEx2Portrait" Subtitle="acObj" Speaker="ShakurasAlly" Actor="RohanaEx2Portrait" Line="01108"><Flags index="NeedsUpdate" value="1"/><Flags index="NeedsTTS" value="1"/></CSound>
    <CSound id="acObj_ShakurasAlly_1134" parent="ACVO_Priority" Portrait="RohanaEx2Portrait" Subtitle="acObj" Speaker="ShakurasAlly" Actor="RohanaEx2Portrait" Line="01134"><Flags index="NeedsUpdate" value="1"/><Flags index="NeedsTTS" value="1"/></CSound>
    <CSound id="acObj_ShakurasAlly_1140" parent="ACVO_Priority" Portrait="RohanaEx2Portrait" Subtitle="acObj" Speaker="ShakurasAlly" Actor="RohanaEx2Portrait" Line="01140"><Flags index="NeedsUpdate" value="1"/><Flags index="NeedsTTS" value="1"/></CSound>
    <CSound id="acObj_ShakurasAlly_1142" parent="ACVO_Priority" Portrait="RohanaEx2Portrait" Subtitle="acObj" Speaker="ShakurasAlly" Actor="RohanaEx2Portrait" Line="01142"><Flags index="NeedsUpdate" value="1"/><Flags index="NeedsTTS" value="1"/></CSound>
    <CSound id="acObj_ShakurasAlly_1146" parent="ACVO_Priority" Portrait="RohanaEx2Portrait" Subtitle="acObj" Speaker="ShakurasAlly" Actor="RohanaEx2Portrait" Line="01146"><Flags index="NeedsUpdate" value="1"/><Flags index="NeedsTTS" value="1"/></CSound>
    <CSound id="acObj_ShakurasAlly_1147" parent="ACVO_Priority" Portrait="RohanaEx2Portrait" Subtitle="acObj" Speaker="ShakurasAlly" Actor="RohanaEx2Portrait" Line="01147"><Flags index="NeedsUpdate" value="1"/><Flags index="NeedsTTS" value="1"/></CSound>
    <CSound id="acObj_ShakurasAlly_1148" parent="ACVO_Priority" Portrait="RohanaEx2Portrait" Subtitle="acObj" Speaker="ShakurasAlly" Actor="RohanaEx2Portrait" Line="01148"><Flags index="NeedsUpdate" value="1"/><Flags index="NeedsTTS" value="1"/></CSound>
    <CSound id="acObj_ShakurasAlly_1149" parent="ACVO_Priority" Portrait="RohanaEx2Portrait" Subtitle="acObj" Speaker="ShakurasAlly" Actor="RohanaEx2Portrait" Line="01149"><Flags index="NeedsUpdate" value="1"/><Flags index="NeedsTTS" value="1"/></CSound>
    <CSound id="acObj_ShakurasAlly_1150" parent="ACVO_Priority" Portrait="RohanaEx2Portrait" Subtitle="acObj" Speaker="ShakurasAlly" Actor="RohanaEx2Portrait" Line="01150"><Flags index="NeedsUpdate" value="1"/><Flags index="NeedsTTS" value="1"/></CSound>
    <CSound id="acObj_ShakurasAlly_1152" parent="ACVO_Priority" Portrait="RohanaEx2Portrait" Subtitle="acObj" Speaker="ShakurasAlly" Actor="RohanaEx2Portrait" Line="01152"><Flags index="NeedsUpdate" value="1"/><Flags index="NeedsTTS" value="1"/></CSound>
    <CSound id="acObj_ShakurasAlly_1154" parent="ACVO_Priority" Portrait="RohanaEx2Portrait" Subtitle="acObj" Speaker="ShakurasAlly" Actor="RohanaEx2Portrait" Line="01154"><Flags index="NeedsUpdate" value="1"/><Flags index="NeedsTTS" value="1"/></CSound>
    <CSound id="acObj_ShakurasAlly_1156" parent="ACVO_Priority" Portrait="RohanaEx2Portrait" Subtitle="acObj" Speaker="ShakurasAlly" Actor="RohanaEx2Portrait" Line="01156"><Flags index="NeedsUpdate" value="1"/><Flags index="NeedsTTS" value="1"/></CSound>
    <CSound id="acObj_ShakurasAlly_1158" parent="ACVO_Priority" Portrait="RohanaEx2Portrait" Subtitle="acObj" Speaker="ShakurasAlly" Actor="RohanaEx2Portrait" Line="01158"><Flags index="NeedsUpdate" value="1"/><Flags index="NeedsTTS" value="1"/></CSound>
    <CSound id="acObj_ShakurasAlly_1160" parent="ACVO_Priority" Portrait="RohanaEx2Portrait" Subtitle="acObj" Speaker="ShakurasAlly" Actor="RohanaEx2Portrait" Line="01160"><Flags index="NeedsUpdate" value="1"/><Flags index="NeedsTTS" value="1"/></CSound>
    <CSound id="acObj_ShakurasAlly_1164" parent="ACVO_Priority" Portrait="RohanaEx2Portrait" Subtitle="acObj" Speaker="ShakurasAlly" Actor="RohanaEx2Portrait" Line="01164"><Flags index="NeedsUpdate" value="1"/><Flags index="NeedsTTS" value="1"/></CSound>
    <CSound id="acObj_ShakurasAlly_1167" parent="ACVO_Priority" Portrait="RohanaEx2Portrait" Subtitle="acObj" Speaker="ShakurasAlly" Actor="RohanaEx2Portrait" Line="01167"><Flags index="NeedsUpdate" value="1"/><Flags index="NeedsTTS" value="1"/></CSound>
    <CSound id="acObj_ShakurasAlly_1170" parent="ACVO_Priority" Portrait="RohanaEx2Portrait" Subtitle="acObj" Speaker="ShakurasAlly" Actor="RohanaEx2Portrait" Line="01170"><Flags index="NeedsUpdate" value="1"/><Flags index="NeedsTTS" value="1"/></CSound>
    <CSound id="acObj_ShakurasAlly_1171" parent="ACVO_Priority" Portrait="RohanaEx2Portrait" Subtitle="acObj" Speaker="ShakurasAlly" Actor="RohanaEx2Portrait" Line="01171"><Flags index="NeedsUpdate" value="1"/><Flags index="NeedsTTS" value="1"/></CSound>
    <CSound id="acObj_ShakurasAlly_1200" parent="ACVO_Priority" Portrait="RohanaEx2Portrait" Subtitle="acObj" Speaker="ShakurasAlly" Actor="RohanaEx2Portrait" Line="01200"><Flags index="NeedsUpdate" value="1"/><Flags index="NeedsTTS" value="1"/></CSound>
    <CSound id="acObj_ShakurasAlly_880" parent="ACVO_Priority" Portrait="RohanaEx2Portrait" Subtitle="acObj" Speaker="ShakurasAlly" Actor="RohanaEx2Portrait" Line="00880"><Flags index="NeedsUpdate" value="1"/><Flags index="NeedsTTS" value="1"/></CSound>
    <CSound id="acObj_ShakurasAlly_881" parent="ACVO_Priority" Portrait="RohanaEx2Portrait" Subtitle="acObj" Speaker="ShakurasAlly" Actor="RohanaEx2Portrait" Line="00881"><Flags index="NeedsUpdate" value="1"/><Flags index="NeedsTTS" value="1"/></CSound>
    <CSound id="acObj_ShakurasAlly_839" parent="ACVO_Priority" Portrait="RohanaEx2Portrait" Subtitle="acObj" Speaker="ShakurasAlly" Actor="RohanaEx2Portrait" Line="00839"><Flags index="NeedsUpdate" value="1"/><Flags index="NeedsTTS" value="1"/></CSound>
    <CSound id="acObj_ShakurasAlly_841" parent="ACVO_Priority" Portrait="RohanaEx2Portrait" Subtitle="acObj" Speaker="ShakurasAlly" Actor="RohanaEx2Portrait" Line="00841"><Flags index="NeedsUpdate" value="1"/><Flags index="NeedsTTS" value="1"/></CSound>
    <CSound id="acObj_ShakurasAlly_842" parent="ACVO_Priority" Portrait="RohanaEx2Portrait" Subtitle="acObj" Speaker="ShakurasAlly" Actor="RohanaEx2Portrait" Line="00842"><Flags index="NeedsUpdate" value="1"/><Flags index="NeedsTTS" value="1"/></CSound>
    <CSound id="acObj_ShakurasAlly_843" parent="ACVO_Priority" Portrait="RohanaEx2Portrait" Subtitle="acObj" Speaker="ShakurasAlly" Actor="RohanaEx2Portrait" Line="00843"><Flags index="NeedsUpdate" value="1"/><Flags index="NeedsTTS" value="1"/></CSound>
    <CSound id="acObj_ShakurasAlly_844" parent="ACVO_Priority" Portrait="RohanaEx2Portrait" Subtitle="acObj" Speaker="ShakurasAlly" Actor="RohanaEx2Portrait" Line="00844"><Flags index="NeedsUpdate" value="1"/><Flags index="NeedsTTS" value="1"/></CSound>
    <CSound id="acObj_ShakurasAlly_845" parent="ACVO_Priority" Portrait="RohanaEx2Portrait" Subtitle="acObj" Speaker="ShakurasAlly" Actor="RohanaEx2Portrait" Line="00845"><Flags index="NeedsUpdate" value="1"/><Flags index="NeedsTTS" value="1"/></CSound>
    <CSound id="acObj_ShakurasAlly_846" parent="ACVO_Priority" Portrait="RohanaEx2Portrait" Subtitle="acObj" Speaker="ShakurasAlly" Actor="RohanaEx2Portrait" Line="00846"><Flags index="NeedsUpdate" value="1"/><Flags index="NeedsTTS" value="1"/></CSound>
    <CSound id="acObj_ShakurasAlly_847" parent="ACVO_Priority" Portrait="RohanaEx2Portrait" Subtitle="acObj" Speaker="ShakurasAlly" Actor="RohanaEx2Portrait" Line="00847"><Flags index="NeedsUpdate" value="1"/><Flags index="NeedsTTS" value="1"/></CSound>
    <CSound id="acObj_ShakurasAlly_855" parent="ACVO_Priority" Portrait="RohanaEx2Portrait" Subtitle="acObj" Speaker="ShakurasAlly" Actor="RohanaEx2Portrait" Line="00855"><Flags index="NeedsUpdate" value="1"/><Flags index="NeedsTTS" value="1"/></CSound>
    <CSound id="acObj_ShakurasAlly_856" parent="ACVO_Priority" Portrait="RohanaEx2Portrait" Subtitle="acObj" Speaker="ShakurasAlly" Actor="RohanaEx2Portrait" Line="00856"><Flags index="NeedsUpdate" value="1"/><Flags index="NeedsTTS" value="1"/></CSound>
    <CSound id="acObj_ShakurasAlly_944" parent="ACVO_Priority" Portrait="RohanaEx2Portrait" Subtitle="acObj" Speaker="ShakurasAlly" Actor="RohanaEx2Portrait" Line="00944"><Flags index="NeedsUpdate" value="1"/><Flags index="NeedsTTS" value="1"/></CSound>
    <CSound id="acObj_ShakurasAlly_946" parent="ACVO_Priority" Portrait="RohanaEx2Portrait" Subtitle="acObj" Speaker="ShakurasAlly" Actor="RohanaEx2Portrait" Line="00946"><Flags index="NeedsUpdate" value="1"/><Flags index="NeedsTTS" value="1"/></CSound>
    <CSound id="acObj_ShakurasAlly_973" parent="ACVO_Priority" Portrait="RohanaEx2Portrait" Subtitle="acObj" Speaker="ShakurasAlly" Actor="RohanaEx2Portrait" Line="00973"><Flags index="NeedsUpdate" value="1"/><Flags index="NeedsTTS" value="1"/></CSound>
    <CSound id="acObj_ShakurasAlly_974" parent="ACVO_Priority" Portrait="RohanaEx2Portrait" Subtitle="acObj" Speaker="ShakurasAlly" Actor="RohanaEx2Portrait" Line="00974"><Flags index="NeedsUpdate" value="1"/><Flags index="NeedsTTS" value="1"/></CSound>
    <CSound id="acObj_ShakurasAlly_975" parent="ACVO_Priority" Portrait="RohanaEx2Portrait" Subtitle="acObj" Speaker="ShakurasAlly" Actor="RohanaEx2Portrait" Line="00975"><Flags index="NeedsUpdate" value="1"/><Flags index="NeedsTTS" value="1"/></CSound>
    <CSound id="acObj_ShakurasAlly_976" parent="ACVO_Priority" Portrait="RohanaEx2Portrait" Subtitle="acObj" Speaker="ShakurasAlly" Actor="RohanaEx2Portrait" Line="00976"><Flags index="NeedsUpdate" value="1"/><Flags index="NeedsTTS" value="1"/></CSound>
    <CSound id="acObj_ShakurasAlly_977" parent="ACVO_Priority" Portrait="RohanaEx2Portrait" Subtitle="acObj" Speaker="ShakurasAlly" Actor="RohanaEx2Portrait" Line="00977"><Flags index="NeedsUpdate" value="1"/><Flags index="NeedsTTS" value="1"/></CSound>
    <CSound id="acObj_ShakurasAlly_836" parent="ACVO_Priority" Portrait="RohanaEx2Portrait" Subtitle="acObj" Speaker="ShakurasAlly" Actor="RohanaEx2Portrait" Line="00836"><Flags index="NeedsUpdate" value="1"/><Flags index="NeedsTTS" value="1"/></CSound>
    <CSound id="acObj_ShakurasAlly_837" parent="ACVO_Priority" Portrait="RohanaEx2Portrait" Subtitle="acObj" Speaker="ShakurasAlly" Actor="RohanaEx2Portrait" Line="00837"><Flags index="NeedsUpdate" value="1"/><Flags index="NeedsTTS" value="1"/></CSound>
    <CSound id="acObj_ShakurasAlly_838" parent="ACVO_Priority" Portrait="RohanaEx2Portrait" Subtitle="acObj" Speaker="ShakurasAlly" Actor="RohanaEx2Portrait" Line="00838"><Flags index="NeedsUpdate" value="1"/><Flags index="NeedsTTS" value="1"/></CSound>
    <CSound id="acObj_ShakurasAlly_840" parent="ACVO_Priority" Portrait="RohanaEx2Portrait" Subtitle="acObj" Speaker="ShakurasAlly" Actor="RohanaEx2Portrait" Line="00840"><Flags index="NeedsUpdate" value="1"/><Flags index="NeedsTTS" value="1"/></CSound>
    <CSound id="acObj_ShakurasAlly_849" parent="ACVO_Priority" Portrait="RohanaEx2Portrait" Subtitle="acObj" Speaker="ShakurasAlly" Actor="RohanaEx2Portrait" Line="00849"><Flags index="NeedsUpdate" value="1"/><Flags index="NeedsTTS" value="1"/></CSound>
    <CSound id="acObj_ShakurasAlly_850" parent="ACVO_Priority" Portrait="RohanaEx2Portrait" Subtitle="acObj" Speaker="ShakurasAlly" Actor="RohanaEx2Portrait" Line="00850"><Flags index="NeedsUpdate" value="1"/><Flags index="NeedsTTS" value="1"/></CSound>
    <CSound id="acObj_ShakurasAlly_851" parent="ACVO_Priority" Portrait="RohanaEx2Portrait" Subtitle="acObj" Speaker="ShakurasAlly" Actor="RohanaEx2Portrait" Line="00851"><Flags index="NeedsUpdate" value="1"/><Flags index="NeedsTTS" value="1"/></CSound>
    <CSound id="acObj_ShakurasAlly_852" parent="ACVO_Priority" Portrait="RohanaEx2Portrait" Subtitle="acObj" Speaker="ShakurasAlly" Actor="RohanaEx2Portrait" Line="00852"><Flags index="NeedsUpdate" value="1"/><Flags index="NeedsTTS" value="1"/></CSound>
    <CSound id="acObj_ShakurasAlly_882" parent="ACVO_Priority" Portrait="RohanaEx2Portrait" Subtitle="acObj" Speaker="ShakurasAlly" Actor="RohanaEx2Portrait" Line="00882"><Flags index="NeedsUpdate" value="1"/><Flags index="NeedsTTS" value="1"/></CSound>
    <CSound id="acObj_ShakurasAlly_887" parent="ACVO_Priority" Portrait="RohanaEx2Portrait" Subtitle="acObj" Speaker="ShakurasAlly" Actor="RohanaEx2Portrait" Line="00887"><Flags index="NeedsUpdate" value="1"/><Flags index="NeedsTTS" value="1"/></CSound>
    <CSound id="acObj_ShakurasAlly_935" parent="ACVO_Priority" Portrait="RohanaEx2Portrait" Subtitle="acObj" Speaker="ShakurasAlly" Actor="RohanaEx2Portrait" Line="00935"><Flags index="NeedsUpdate" value="1"/><Flags index="NeedsTTS" value="1"/></CSound>
    <CSound id="acObj_ShakurasAlly_936" parent="ACVO_Priority" Portrait="RohanaEx2Portrait" Subtitle="acObj" Speaker="ShakurasAlly" Actor="RohanaEx2Portrait" Line="00936"><Flags index="NeedsUpdate" value="1"/><Flags index="NeedsTTS" value="1"/></CSound>
    <CSound id="acObj_ShakurasAlly_937" parent="ACVO_Priority" Portrait="RohanaEx2Portrait" Subtitle="acObj" Speaker="ShakurasAlly" Actor="RohanaEx2Portrait" Line="00937"><Flags index="NeedsUpdate" value="1"/><Flags index="NeedsTTS" value="1"/></CSound>
    <CSound id="acObj_ShakurasAlly_938" parent="ACVO_Priority" Portrait="RohanaEx2Portrait" Subtitle="acObj" Speaker="ShakurasAlly" Actor="RohanaEx2Portrait" Line="00938"><Flags index="NeedsUpdate" value="1"/><Flags index="NeedsTTS" value="1"/></CSound>
    <CSound id="acObj_ShakurasAlly_939" parent="ACVO_Priority" Portrait="RohanaEx2Portrait" Subtitle="acObj" Speaker="ShakurasAlly" Actor="RohanaEx2Portrait" Line="00939"><Flags index="NeedsUpdate" value="1"/><Flags index="NeedsTTS" value="1"/></CSound>
    <CSound id="acObj_ShakurasAlly_940" parent="ACVO_Priority" Portrait="RohanaEx2Portrait" Subtitle="acObj" Speaker="ShakurasAlly" Actor="RohanaEx2Portrait" Line="00940"><Flags index="NeedsUpdate" value="1"/><Flags index="NeedsTTS" value="1"/></CSound>
    <CSound id="acObj_ShakurasAlly_941" parent="ACVO_Priority" Portrait="RohanaEx2Portrait" Subtitle="acObj" Speaker="ShakurasAlly" Actor="RohanaEx2Portrait" Line="00941"><Flags index="NeedsUpdate" value="1"/><Flags index="NeedsTTS" value="1"/></CSound>
    <CSound id="acObj_ShakurasAlly_942" parent="ACVO_Priority" Portrait="RohanaEx2Portrait" Subtitle="acObj" Speaker="ShakurasAlly" Actor="RohanaEx2Portrait" Line="00942"><Flags index="NeedsUpdate" value="1"/><Flags index="NeedsTTS" value="1"/></CSound>
    <CSound id="acObj_ShakurasAlly_943" parent="ACVO_Priority" Portrait="RohanaEx2Portrait" Subtitle="acObj" Speaker="ShakurasAlly" Actor="RohanaEx2Portrait" Line="00943"><Flags index="NeedsUpdate" value="1"/><Flags index="NeedsTTS" value="1"/></CSound>
    <CSound id="acObj_ShakurasAlly_945" parent="ACVO_Priority" Portrait="RohanaEx2Portrait" Subtitle="acObj" Speaker="ShakurasAlly" Actor="RohanaEx2Portrait" Line="00945"><Flags index="NeedsUpdate" value="1"/><Flags index="NeedsTTS" value="1"/></CSound>
    <CSound id="acObj_ShakurasAlly_947" parent="ACVO_Priority" Portrait="RohanaEx2Portrait" Subtitle="acObj" Speaker="ShakurasAlly" Actor="RohanaEx2Portrait" Line="00947"><Flags index="NeedsUpdate" value="1"/><Flags index="NeedsTTS" value="1"/></CSound>
    <CSound id="acObj_ShakurasAlly_948" parent="ACVO_Priority" Portrait="RohanaEx2Portrait" Subtitle="acObj" Speaker="ShakurasAlly" Actor="RohanaEx2Portrait" Line="00948"><Flags index="NeedsUpdate" value="1"/><Flags index="NeedsTTS" value="1"/></CSound>
    <CSound id="acObj_ShakurasAlly_949" parent="ACVO_Priority" Portrait="RohanaEx2Portrait" Subtitle="acObj" Speaker="ShakurasAlly" Actor="RohanaEx2Portrait" Line="00949"><Flags index="NeedsUpdate" value="1"/><Flags index="NeedsTTS" value="1"/></CSound>
    <CSound id="acObj_ShakurasAlly_950" parent="ACVO_Priority" Portrait="RohanaEx2Portrait" Subtitle="acObj" Speaker="ShakurasAlly" Actor="RohanaEx2Portrait" Line="00950"><Flags index="NeedsUpdate" value="1"/><Flags index="NeedsTTS" value="1"/></CSound>
    <CSound id="acObj_ShakurasAlly_987" parent="ACVO_Priority" Portrait="RohanaEx2Portrait" Subtitle="acObj" Speaker="ShakurasAlly" Actor="RohanaEx2Portrait" Line="00987"><Flags index="NeedsUpdate" value="1"/><Flags index="NeedsTTS" value="1"/></CSound>
    <CSound id="acObj_ShakurasAlly_1088" parent="ACVO_Priority" Portrait="RohanaEx2Portrait" Subtitle="acObj" Speaker="ShakurasAlly" Actor="RohanaEx2Portrait" Line="01088"><Flags index="NeedsUpdate" value="1"/><Flags index="NeedsTTS" value="1"/></CSound>
    <CSound id="acObj_ShakurasAlly_1089" parent="ACVO_Priority" Portrait="RohanaEx2Portrait" Subtitle="acObj" Speaker="ShakurasAlly" Actor="RohanaEx2Portrait" Line="01089"><Flags index="NeedsUpdate" value="1"/><Flags index="NeedsTTS" value="1"/></CSound>
    <CSound id="acObj_ShakurasAlly_1090" parent="ACVO_Priority" Portrait="RohanaEx2Portrait" Subtitle="acObj" Speaker="ShakurasAlly" Actor="RohanaEx2Portrait" Line="01090"><Flags index="NeedsUpdate" value="1"/><Flags index="NeedsTTS" value="1"/></CSound>
    <CSound id="acObj_ShakurasAlly_1091" parent="ACVO_Priority" Portrait="RohanaEx2Portrait" Subtitle="acObj" Speaker="ShakurasAlly" Actor="RohanaEx2Portrait" Line="01091"><Flags index="NeedsUpdate" value="1"/><Flags index="NeedsTTS" value="1"/></CSound>
    <CSound id="acObj_ShakurasAlly_1092" parent="ACVO_Priority" Portrait="RohanaEx2Portrait" Subtitle="acObj" Speaker="ShakurasAlly" Actor="RohanaEx2Portrait" Line="01092"><Flags index="NeedsUpdate" value="1"/><Flags index="NeedsTTS" value="1"/></CSound>
    <CSound id="acObj_ShakurasAlly_1093" parent="ACVO_Priority" Portrait="RohanaEx2Portrait" Subtitle="acObj" Speaker="ShakurasAlly" Actor="RohanaEx2Portrait" Line="01093"><Flags index="NeedsUpdate" value="1"/><Flags index="NeedsTTS" value="1"/></CSound>
    <CSound id="acObj_ShakurasAlly_1094" parent="ACVO_Priority" Portrait="RohanaEx2Portrait" Subtitle="acObj" Speaker="ShakurasAlly" Actor="RohanaEx2Portrait" Line="01094"><Flags index="NeedsUpdate" value="1"/><Flags index="NeedsTTS" value="1"/></CSound>
    <CSound id="acObj_ShakurasAlly_1095" parent="ACVO_Priority" Portrait="RohanaEx2Portrait" Subtitle="acObj" Speaker="ShakurasAlly" Actor="RohanaEx2Portrait" Line="01095"><Flags index="NeedsUpdate" value="1"/><Flags index="NeedsTTS" value="1"/></CSound>
    <CSound id="acObj_ShakurasAlly_1097" parent="ACVO_Priority" Portrait="RohanaEx2Portrait" Subtitle="acObj" Speaker="ShakurasAlly" Actor="RohanaEx2Portrait" Line="01097"><Flags index="NeedsUpdate" value="1"/><Flags index="NeedsTTS" value="1"/></CSound>
    <CSound id="acObj_ShakurasAlly_1099" parent="ACVO_Priority" Portrait="RohanaEx2Portrait" Subtitle="acObj" Speaker="ShakurasAlly" Actor="RohanaEx2Portrait" Line="01099"><Flags index="NeedsUpdate" value="1"/><Flags index="NeedsTTS" value="1"/></CSound>
    <CSound id="acObj_ShakurasAlly_1101" parent="ACVO_Priority" Portrait="RohanaEx2Portrait" Subtitle="acObj" Speaker="ShakurasAlly" Actor="RohanaEx2Portrait" Line="01101"><Flags index="NeedsUpdate" value="1"/><Flags index="NeedsTTS" value="1"/></CSound>
    <CSound id="acObj_ShakurasAlly_1103" parent="ACVO_Priority" Portrait="RohanaEx2Portrait" Subtitle="acObj" Speaker="ShakurasAlly" Actor="RohanaEx2Portrait" Line="01103"><Flags index="NeedsUpdate" value="1"/><Flags index="NeedsTTS" value="1"/></CSound>
    <CSound id="acObj_ShakurasAlly_1104" parent="ACVO_Priority" Portrait="RohanaEx2Portrait" Subtitle="acObj" Speaker="ShakurasAlly" Actor="RohanaEx2Portrait" Line="01104"><Flags index="NeedsUpdate" value="1"/><Flags index="NeedsTTS" value="1"/></CSound>
    <CSound id="acObj_ShakurasAlly_1106" parent="ACVO_Priority" Portrait="RohanaEx2Portrait" Subtitle="acObj" Speaker="ShakurasAlly" Actor="RohanaEx2Portrait" Line="01106"><Flags index="NeedsUpdate" value="1"/><Flags index="NeedsTTS" value="1"/></CSound>
    <CSound id="acObj_ShakurasAlly_1107" parent="ACVO_Priority" Portrait="RohanaEx2Portrait" Subtitle="acObj" Speaker="ShakurasAlly" Actor="RohanaEx2Portrait" Line="01107"><Flags index="NeedsUpdate" value="1"/><Flags index="NeedsTTS" value="1"/></CSound>
    <CSound id="acObj_ShakurasAlly_1133" parent="ACVO_Priority" Portrait="RohanaEx2Portrait" Subtitle="acObj" Speaker="ShakurasAlly" Actor="RohanaEx2Portrait" Line="01133"><Flags index="NeedsUpdate" value="1"/><Flags index="NeedsTTS" value="1"/></CSound>
    <CSound id="acObj_ShakurasAlly_1135" parent="ACVO_Priority" Portrait="RohanaEx2Portrait" Subtitle="acObj" Speaker="ShakurasAlly" Actor="RohanaEx2Portrait" Line="01135"><Flags index="NeedsUpdate" value="1"/><Flags index="NeedsTTS" value="1"/></CSound>
    <CSound id="acObj_ShakurasAlly_1136" parent="ACVO_Priority" Portrait="RohanaEx2Portrait" Subtitle="acObj" Speaker="ShakurasAlly" Actor="RohanaEx2Portrait" Line="01136"><Flags index="NeedsUpdate" value="1"/><Flags index="NeedsTTS" value="1"/></CSound>
    <CSound id="acObj_ShakurasAlly_1137" parent="ACVO_Priority" Portrait="RohanaEx2Portrait" Subtitle="acObj" Speaker="ShakurasAlly" Actor="RohanaEx2Portrait" Line="01137"><Flags index="NeedsUpdate" value="1"/><Flags index="NeedsTTS" value="1"/></CSound>
    <CSound id="acObj_ShakurasAlly_1138" parent="ACVO_Priority" Portrait="RohanaEx2Portrait" Subtitle="acObj" Speaker="ShakurasAlly" Actor="RohanaEx2Portrait" Line="01138"><Flags index="NeedsUpdate" value="1"/><Flags index="NeedsTTS" value="1"/></CSound>
    <CSound id="acObj_ShakurasAlly_1139" parent="ACVO_Priority" Portrait="RohanaEx2Portrait" Subtitle="acObj" Speaker="ShakurasAlly" Actor="RohanaEx2Portrait" Line="01139"><Flags index="NeedsUpdate" value="1"/><Flags index="NeedsTTS" value="1"/></CSound>
    <CSound id="acObj_ShakurasAlly_1141" parent="ACVO_Priority" Portrait="RohanaEx2Portrait" Subtitle="acObj" Speaker="ShakurasAlly" Actor="RohanaEx2Portrait" Line="01141"><Flags index="NeedsUpdate" value="1"/><Flags index="NeedsTTS" value="1"/></CSound>
    <CSound id="acObj_ShakurasAlly_1143" parent="ACVO_Priority" Portrait="RohanaEx2Portrait" Subtitle="acObj" Speaker="ShakurasAlly" Actor="RohanaEx2Portrait" Line="01143"><Flags index="NeedsUpdate" value="1"/><Flags index="NeedsTTS" value="1"/></CSound>
    <CSound id="acObj_ShakurasAlly_1145" parent="ACVO_Priority" Portrait="RohanaEx2Portrait" Subtitle="acObj" Speaker="ShakurasAlly" Actor="RohanaEx2Portrait" Line="01145"><Flags index="NeedsUpdate" value="1"/><Flags index="NeedsTTS" value="1"/></CSound>
    <CSound id="acObj_ShakurasAlly_1151" parent="ACVO_Priority" Portrait="RohanaEx2Portrait" Subtitle="acObj" Speaker="ShakurasAlly" Actor="RohanaEx2Portrait" Line="01151"><Flags index="NeedsUpdate" value="1"/><Flags index="NeedsTTS" value="1"/></CSound>
    <CSound id="acObj_ShakurasAlly_1153" parent="ACVO_Priority" Portrait="RohanaEx2Portrait" Subtitle="acObj" Speaker="ShakurasAlly" Actor="RohanaEx2Portrait" Line="01153"><Flags index="NeedsUpdate" value="1"/><Flags index="NeedsTTS" value="1"/></CSound>
    <CSound id="acObj_ShakurasAlly_1155" parent="ACVO_Priority" Portrait="RohanaEx2Portrait" Subtitle="acObj" Speaker="ShakurasAlly" Actor="RohanaEx2Portrait" Line="01155"><Flags index="NeedsUpdate" value="1"/><Flags index="NeedsTTS" value="1"/></CSound>
    <CSound id="acObj_ShakurasAlly_1157" parent="ACVO_Priority" Portrait="RohanaEx2Portrait" Subtitle="acObj" Speaker="ShakurasAlly" Actor="RohanaEx2Portrait" Line="01157"><Flags index="NeedsUpdate" value="1"/><Flags index="NeedsTTS" value="1"/></CSound>
    <CSound id="acObj_ShakurasAlly_1159" parent="ACVO_Priority" Portrait="RohanaEx2Portrait" Subtitle="acObj" Speaker="ShakurasAlly" Actor="RohanaEx2Portrait" Line="01159"><Flags index="NeedsUpdate" value="1"/><Flags index="NeedsTTS" value="1"/></CSound>
    <CSound id="acObj_ShakurasAlly_1161" parent="ACVO_Priority" Portrait="RohanaEx2Portrait" Subtitle="acObj" Speaker="ShakurasAlly" Actor="RohanaEx2Portrait" Line="01161"><Flags index="NeedsUpdate" value="1"/><Flags index="NeedsTTS" value="1"/></CSound>
    <CSound id="acObj_ShakurasAlly_1162" parent="ACVO_Priority" Portrait="RohanaEx2Portrait" Subtitle="acObj" Speaker="ShakurasAlly" Actor="RohanaEx2Portrait" Line="01162"><Flags index="NeedsUpdate" value="1"/><Flags index="NeedsTTS" value="1"/></CSound>
    <CSound id="acObj_ShakurasAlly_1163" parent="ACVO_Priority" Portrait="RohanaEx2Portrait" Subtitle="acObj" Speaker="ShakurasAlly" Actor="RohanaEx2Portrait" Line="01163"><Flags index="NeedsUpdate" value="1"/><Flags index="NeedsTTS" value="1"/></CSound>
    <CSound id="acObj_ShakurasAlly_1165" parent="ACVO_Priority" Portrait="RohanaEx2Portrait" Subtitle="acObj" Speaker="ShakurasAlly" Actor="RohanaEx2Portrait" Line="01165"><Flags index="NeedsUpdate" value="1"/><Flags index="NeedsTTS" value="1"/></CSound>
    <CSound id="acObj_ShakurasAlly_1166" parent="ACVO_Priority" Portrait="RohanaEx2Portrait" Subtitle="acObj" Speaker="ShakurasAlly" Actor="RohanaEx2Portrait" Line="01166"><Flags index="NeedsUpdate" value="1"/><Flags index="NeedsTTS" value="1"/></CSound>
    <CSound id="acObj_ShakurasAlly_1168" parent="ACVO_Priority" Portrait="RohanaEx2Portrait" Subtitle="acObj" Speaker="ShakurasAlly" Actor="RohanaEx2Portrait" Line="01168"><Flags index="NeedsUpdate" value="1"/><Flags index="NeedsTTS" value="1"/></CSound>
    <CSound id="acObj_ShakurasAlly_1169" parent="ACVO_Priority" Portrait="RohanaEx2Portrait" Subtitle="acObj" Speaker="ShakurasAlly" Actor="RohanaEx2Portrait" Line="01169"><Flags index="NeedsUpdate" value="1"/><Flags index="NeedsTTS" value="1"/></CSound>
    <CSound id="acObj_ShakurasAlly_1191" parent="ACVO_Priority" Portrait="RohanaEx2Portrait" Subtitle="acObj" Speaker="ShakurasAlly" Actor="RohanaEx2Portrait" Line="01191"><Flags index="NeedsUpdate" value="1"/><Flags index="NeedsTTS" value="1"/></CSound>
    <CSound id="acObj_ShakurasAlly_1192" parent="ACVO_Priority" Portrait="RohanaEx2Portrait" Subtitle="acObj" Speaker="ShakurasAlly" Actor="RohanaEx2Portrait" Line="01192"><Flags index="NeedsUpdate" value="1"/><Flags index="NeedsTTS" value="1"/></CSound>
    <CSound id="acObj_ShakurasAlly_1193" parent="ACVO_Priority" Portrait="RohanaEx2Portrait" Subtitle="acObj" Speaker="ShakurasAlly" Actor="RohanaEx2Portrait" Line="01193"><Flags index="NeedsUpdate" value="1"/><Flags index="NeedsTTS" value="1"/></CSound>
    <CSound id="acObj_ShakurasAlly_1198" parent="ACVO_Priority" Portrait="RohanaEx2Portrait" Subtitle="acObj" Speaker="ShakurasAlly" Actor="RohanaEx2Portrait" Line="01198"><Flags index="NeedsUpdate" value="1"/><Flags index="NeedsTTS" value="1"/></CSound>
    <CSound id="acObj_ShakurasAlly_1199" parent="ACVO_Priority" Portrait="RohanaEx2Portrait" Subtitle="acObj" Speaker="ShakurasAlly" Actor="RohanaEx2Portrait" Line="01199"><Flags index="NeedsUpdate" value="1"/><Flags index="NeedsTTS" value="1"/></CSound>
    <CSound id="acObj_ShakurasAlly_1220" parent="ACVO_Priority" Portrait="RohanaEx2Portrait" Subtitle="acObj" Speaker="ShakurasAlly" Actor="RohanaEx2Portrait" Line="01220"><Flags index="NeedsUpdate" value="1"/><Flags index="NeedsTTS" value="1"/></CSound>
    <CSound id="acObj_ShakurasAlly_1221" parent="ACVO_Priority" Portrait="RohanaEx2Portrait" Subtitle="acObj" Speaker="ShakurasAlly" Actor="RohanaEx2Portrait" Line="01221"><Flags index="NeedsUpdate" value="1"/><Flags index="NeedsTTS" value="1"/></CSound>

</Catalog>